lumberjack/__init__.py
lumberjack/filters.py
lumberjack/listener.py
lumberjack/redis.py
lumberjack/serialize.py
lumberjack/streams.py
lumberjack/utils.py
lumberjack/warnings.py
lumberjack/watcher.py
lumberjack/zmq.py
lumberjack/config/__init__.py
lumberjack/config/base.cfg
lumberjack/config/redis.cfg
lumberjack/config/stream.cfg
lumberjack/config/zmq.cfg
lumberjack_logging-0.1.0.dist-info/DESCRIPTION.rst
lumberjack_logging-0.1.0.dist-info/METADATA
lumberjack_logging-0.1.0.dist-info/RECORD
lumberjack_logging-0.1.0.dist-info/WHEEL
lumberjack_logging-0.1.0.dist-info/entry_points.txt
lumberjack_logging-0.1.0.dist-info/metadata.json
lumberjack_logging-0.1.0.dist-info/top_level.txt
