Metadata-Version: 2.0
Name: lumberjack-logging
Version: 0.1.0
Summary: Logging tools.
Home-page: UNKNOWN
Author: Alexander Rudy
Author-email: alex.rudy@gmail.com
License: UNKNOWN
Platform: UNKNOWN
Classifier: Programming Language :: Python :: 2
Classifier: Programming Language :: Python :: 3
Classifier: Intended Audience :: Developers
Classifier: License :: OSI Approved :: MIT License
Classifier: Topic :: Software Development :: Libraries
Classifier: Topic :: System :: Logging
Classifier: Topic :: Utilities
Requires-Dist: six
